mtts/__init__.py
mtts/mtts_env_basis
mtts/mtts_http.py
mtts/audio/__init__.py
mtts/audio/tts_api.py
mtts/mtts_utils/__init__.py
mtts/mtts_utils/locater.py
mi_mtts-1.0.2.post2.dist-info/METADATA
mi_mtts-1.0.2.post2.dist-info/WHEEL
mi_mtts-1.0.2.post2.dist-info/top_level.txt
mi_mtts-1.0.2.post2.dist-info/RECORD
