Metadata-Version: 2.1
Name: mi-mtts
Version: 1.0.2.post2
Summary: MAICA MTTS (Backend)
Home-page: https://github.com/Mon1-innovation/MAICA-MTTS
Author: EdgeInfinity
Author-email: dcc@monika.love
Classifier: Programming Language :: Python :: 3
Classifier: License :: OSI Approved :: MIT License
Classifier: Operating System :: OS Independent
Requires-Python: >=3.12
Requires-Dist: mi-maica>=1.1.3.post2
Requires-Dist: pydub>=0.25.1
Requires-Dist: setuptools==70.0.0
